MANIFEST.in
README.rst
TITLE.txt
lh-agpl3-LICENSE.txt
setup.py
blee/__init__.py
blee.egg-info/PKG-INFO
blee.egg-info/SOURCES.txt
blee.egg-info/dependency_links.txt
blee.egg-info/not-zip-safe
blee.egg-info/top_level.txt